playground.py
src/pytest-dot-only_pkcopley/__init__.py
src/pytest-dot-only_pkcopley/conftest.py
venv/lib/python3.11/site-packages/py.py
venv/lib/python3.11/site-packages/_distutils_hack/__init__.py
venv/lib/python3.11/site-packages/_distutils_hack/override.py
venv/lib/python3.11/site-packages/_pytest/__init__.py
venv/lib/python3.11/site-packages/_pytest/_argcomplete.py
venv/lib/python3.11/site-packages/_pytest/_version.py
venv/lib/python3.11/site-packages/_pytest/cacheprovider.py
venv/lib/python3.11/site-packages/_pytest/capture.py
venv/lib/python3.11/site-packages/_pytest/compat.py
venv/lib/python3.11/site-packages/_pytest/debugging.py
venv/lib/python3.11/site-packages/_pytest/deprecated.py
venv/lib/python3.11/site-packages/_pytest/doctest.py
venv/lib/python3.11/site-packages/_pytest/faulthandler.py
venv/lib/python3.11/site-packages/_pytest/fixtures.py
venv/lib/python3.11/site-packages/_pytest/freeze_support.py
venv/lib/python3.11/site-packages/_pytest/helpconfig.py
venv/lib/python3.11/site-packages/_pytest/hookspec.py
venv/lib/python3.11/site-packages/_pytest/junitxml.py
venv/lib/python3.11/site-packages/_pytest/legacypath.py
venv/lib/python3.11/site-packages/_pytest/logging.py
venv/lib/python3.11/site-packages/_pytest/main.py
venv/lib/python3.11/site-packages/_pytest/monkeypatch.py
venv/lib/python3.11/site-packages/_pytest/nodes.py
venv/lib/python3.11/site-packages/_pytest/nose.py
venv/lib/python3.11/site-packages/_pytest/outcomes.py
venv/lib/python3.11/site-packages/_pytest/pastebin.py
venv/lib/python3.11/site-packages/_pytest/pathlib.py
venv/lib/python3.11/site-packages/_pytest/pytester.py
venv/lib/python3.11/site-packages/_pytest/pytester_assertions.py
venv/lib/python3.11/site-packages/_pytest/python.py
venv/lib/python3.11/site-packages/_pytest/python_api.py
venv/lib/python3.11/site-packages/_pytest/python_path.py
venv/lib/python3.11/site-packages/_pytest/recwarn.py
venv/lib/python3.11/site-packages/_pytest/reports.py
pytest_dot_only_pkcopley-0.0.1.dist-info/METADATA
pytest_dot_only_pkcopley-0.0.1.dist-info/WHEEL
pytest_dot_only_pkcopley-0.0.1.dist-info/RECORD
